 {
  "trainings": [
    {
      "title": "فيزياء",
   "image": "https://raw.githubusercontent.com/fefeglu8/effepdf/refs/heads/main/Screenshot_44.png",
      "lessons": [
                {
                    "title": "تسريبات فيزياء",
                    "quizzes": [
                        {
                            "title": "تسريبات فيزياء - اضغط هنا للبدء"
                        }
                    ]
                },
   {
      "title": "كيمياء",
   "image": "https://raw.githubusercontent.com/fefeglu8/effepdf/refs/heads/main/Screenshot_44.png",
      "lessons": [
        { "title": "تسريبات كيمياء" }
      ]
    },
   {
      "title": "رياضيات",
   "image": "https://raw.githubusercontent.com/fefeglu8/effepdf/refs/heads/main/Screenshot_44.png",
      "lessons": [
        { "title": "تسريبات رياضيات" }
      ]
    },
   {
      "title": "الاحياء",
   "image": "https://raw.githubusercontent.com/fefeglu8/effepdf/refs/heads/main/Screenshot_44.png",
      "lessons": [
        { "title": "تسريبات الاحياء" }
      ]
    }
  ],
  "files": [
    { "name": "قريبا", "url": "https://..." }
  ]
}
